py_ezbar/__init__.py
py_ezbar/bar_styles.py
py_ezbar/progress_bar.py
py_ezbar-0.1.2.dist-info/LICENSE
py_ezbar-0.1.2.dist-info/METADATA
py_ezbar-0.1.2.dist-info/WHEEL
py_ezbar-0.1.2.dist-info/top_level.txt
py_ezbar-0.1.2.dist-info/RECORD
