Metadata-Version: 2.1
Name: py-ezbar
Version: 0.1.2
Summary: Simple progress bar for terminal
Home-page: https://github.com/kdrkrgz/ez-bar
Author: kadir-karagoz
Author-email: Kadir Karagoz <kadir@kadirkaragoz.com>
License: The MIT License (MIT)
Project-URL: Home, https://github.com/kdrkrgz/ez-bar
Keywords: progress,bar,terminal
Classifier: License :: OSI Approved :: MIT License
Requires-Python: >=3.6
License-File: LICENSE
